table2html/__init__.py
table2html/main.py
table2html/models/__init__.py
table2html/models/column_detection.pt
table2html/models/row_detection.pt
table2html/models/table_detection.pt
table2html/source/__init__.py
table2html/source/ocr_engine.py
table2html/source/structure_detector.py
table2html/source/table_detector.py
table2html/source/table_processor.py
table2html/source/utils.py
table2html-1.4.2.dist-info/LICENSE
table2html-1.4.2.dist-info/METADATA
table2html-1.4.2.dist-info/WHEEL
table2html-1.4.2.dist-info/top_level.txt
table2html-1.4.2.dist-info/RECORD
