Metadata-Version: 2.1
Name: table2html
Version: 1.4.2
Summary: Detect and convert table image to html table
Author: TraiPPN
Author-email: phamphungoctraivl@gmail.com
License: Apache License 2.0
Requires-Python: >=3.7
License-File: LICENSE
Requires-Dist: akaocr==2.1.4
Requires-Dist: numpy==2.1.3
Requires-Dist: opencv_python==4.10.0.84
Requires-Dist: ultralytics==8.3.14
Requires-Dist: onnxruntime==1.20.0
Requires-Dist: onnx==1.17.0
